pai/__init__.py
pai/main.py
pai/spinner.py
pipe_pai_tool-0.1.3.dist-info/licenses/LICENSE
pipe_pai_tool-0.1.3.dist-info/METADATA
pipe_pai_tool-0.1.3.dist-info/WHEEL
pipe_pai_tool-0.1.3.dist-info/entry_points.txt
pipe_pai_tool-0.1.3.dist-info/top_level.txt
pipe_pai_tool-0.1.3.dist-info/RECORD
