Metadata-Version: 2.4
Name: pipe-pai-tool
Version: 0.1.3
Summary: pipe-pai is a simple command-line tool that allows you to interact with OpenAI models through Unix pipes
Requires-Python: >=3.13
License-File: LICENSE
Requires-Dist: openai>=0.27.0
Requires-Dist: typer>=0.16.0
Dynamic: license-file
